{"type":"FeatureCollection","features":[{"type":"Feature","geometry":{"type":"Point","coordinates":[-111.0250324,54.3087329]},"properties":{"uwi":"100132906107W400","operator":"Vantage Point Resources Inc.","formation":"Clearwater","field_name":"SUGDEN","well_fluid_type":"Gas","fluid_type":"gas","well_status":"Active","recent_oil":0,"cumulative_oil":0,"recent_gas":15.30000019073486,"recent_water":0,"recent_steam_injection":0,"last_production_date":"2026-01-01","spud_date":"2001-12-17","op_status":"normal"}}]}