{"type":"FeatureCollection","features":[{"type":"Feature","geometry":{"type":"Point","coordinates":[-119.6098148,55.2790866]},"properties":{"uwi":"100053407211W600","operator":"Yoho Resources Inc.","formation":"Bluesky","field_name":"SINCLAIR","well_fluid_type":"Gas","fluid_type":"gas","well_status":"Active","recent_oil":0,"cumulative_oil":0,"recent_gas":144.1000061035156,"recent_water":2.400000095367432,"recent_steam_injection":0,"last_production_date":"2026-01-01","spud_date":"2006-07-01","op_status":"normal"}}]}