{"type":"FeatureCollection","features":[{"type":"Feature","geometry":{"type":"Point","coordinates":[-119.6098148,55.2790866]},"properties":{"uwi":"100053407211W600","operator":"Yoho Resources Inc.","formation":"Bluesky","field_name":"SINCLAIR","well_fluid_type":"Gas","fluid_type":"gas","well_status":"Active","recent_oil":0,"cumulative_oil":0,"recent_gas":6243.69189453125,"recent_water":2.400000095367432,"recent_steam_injection":0,"last_production_date":"2/28/26","spud_date":"6/30/06","op_status":"normal"}}]}