{"type":"FeatureCollection","features":[{"type":"Feature","geometry":{"type":"Point","coordinates":[-116.6194286,53.9257008]},"properties":{"uwi":"100061605718W500","operator":"Journey Energy Inc.","formation":"Bluesky","field_name":"PINE CREEK","well_fluid_type":"Gas","fluid_type":"gas","well_status":"Active","recent_oil":0,"cumulative_oil":0,"recent_gas":8931.1630859375,"recent_water":8.600000381469727,"recent_steam_injection":0,"last_production_date":"2/28/26","spud_date":"3/9/94","op_status":"normal"}},{"type":"Feature","geometry":{"type":"Point","coordinates":[-116.6089526,53.9375139]},"properties":{"uwi":"100022105718W500","operator":"Journey Energy Inc.","formation":"Bluesky","field_name":"PINE CREEK","well_fluid_type":"Gas","fluid_type":"gas","well_status":"Active","recent_oil":0,"cumulative_oil":0,"recent_gas":769.866943359375,"recent_water":3.400000095367432,"recent_steam_injection":0,"last_production_date":"2/28/26","spud_date":"9/4/94","op_status":"normal"}},{"type":"Feature","geometry":{"type":"Point","coordinates":[-116.5930276,53.9321509]},"properties":{"uwi":"100131505718W500","operator":"Journey Energy Inc.","formation":"Bluesky","field_name":"PINE CREEK","well_fluid_type":"Gas","fluid_type":"gas","well_status":"Active","recent_oil":0,"cumulative_oil":0,"recent_gas":2613.309814453125,"recent_water":1.299999952316284,"recent_steam_injection":0,"last_production_date":"2/28/26","spud_date":"3/6/95","op_status":"normal"}},{"type":"Feature","geometry":{"type":"Point","coordinates":[-116.5912326,53.9402159]},"properties":{"uwi":"100072205718W500","operator":"Journey Energy Inc.","formation":"Bluesky","field_name":"PINE CREEK","well_fluid_type":"Gas","fluid_type":"gas","well_status":"Active","recent_oil":0,"cumulative_oil":0,"recent_gas":4636.859375,"recent_water":0,"recent_steam_injection":0,"last_production_date":"2/28/26","spud_date":"10/31/95","op_status":"normal"}}]}